pynoddy/Copy of history.py
pynoddy/__init__.py
pynoddy/check_pynoddy.py
pynoddy/events.py
pynoddy/history.py
pynoddy/info_workshop_program.py
pynoddy/output.py
pynoddy/stochastic_events.py
pynoddy/test_pynoddy.py
pynoddy/experiment/__init__.py
pynoddy/experiment/monte_carlo.py
pynoddy/experiment/sensitivity_analysis.py
pynoddy/experiment/topology_analysis.py
pynoddy/experiment/uncertainty_analysis.py
pynoddy/experiment/util/__init__.py
pynoddy/experiment/util/hive_plot.py
pynoddy/experiment/util/sampling.py
pynoddy-1.1.dist-info/DESCRIPTION.rst
pynoddy-1.1.dist-info/METADATA
pynoddy-1.1.dist-info/RECORD
pynoddy-1.1.dist-info/WHEEL
pynoddy-1.1.dist-info/metadata.json
pynoddy-1.1.dist-info/top_level.txt
