Metadata-Version: 2.0
Name: pynoddy
Version: 1.1
Summary: Python wrappers for kinematic geological simulations with Noddy
Home-page: http://github.com/flohorovicic/pynoddy
Author: Florian Wellmann, Mark Jessell, Sam Thiele
Author-email: flohorovicic@gmail.com
License: GPL
Platform: UNKNOWN
Classifier: Development Status :: 4 - Beta
Classifier: Intended Audience :: Science/Research
Classifier: Programming Language :: Python :: 3.6
Classifier: Intended Audience :: Education
Classifier: Topic :: Education
Classifier: Topic :: Scientific/Engineering
Classifier: Topic :: Scientific/Engineering :: Physics
Classifier: Topic :: Scientific/Engineering :: Visualization
Classifier: License :: OSI Approved :: MIT License
Requires-Dist: SALib
Requires-Dist: pyevtk
